{
  "version": "2010-05-08",
  "endpoint": "iam.amazonaws.com",
  "metadata": {
    "xmlnamespace": "https://iam.amazonaws.com/doc/2010-05-08/",
    "service_full_name": "AWS Identity and Access Management",
    "service_abbreviation": "IAM",
    "service_class_name": "IAM"
  },
  "plugins": [
    "Seahorse::Client::Plugins::RestfulBindings",
    "Seahorse::Client::Plugins::ContentLength",
    "Aws::Plugins::RetryErrors",
    "Aws::Plugins::GlobalConfiguration",
    "Aws::Plugins::RegionalEndpoint",
    "Aws::Plugins::Credentials",
    "Aws::Plugins::QueryProtocol",
    "Aws::Plugins::SignatureV4"
  ],
  "operations": {
    "add_role_to_instance_profile": {
      "name": "AddRoleToInstanceProfile",
      "http_method": "POST",
      "http_path": "/",
      "input": {
        "type": "input",
        "members": {
          "instance_profile_name": {
            "type": "string",
            "required": true,
            "serialized_name": "InstanceProfileName"
          },
          "role_name": {
            "type": "string",
            "required": true,
            "serialized_name": "RoleName"
          }
        }
      }
    },
    "add_user_to_group": {
      "name": "AddUserToGroup",
      "http_method": "POST",
      "http_path": "/",
      "input": {
        "type": "input",
        "members": {
          "group_name": {
            "type": "string",
            "required": true,
            "serialized_name": "GroupName"
          },
          "user_name": {
            "type": "string",
            "required": true,
            "serialized_name": "UserName"
          }
        }
      }
    },
    "change_password": {
      "name": "ChangePassword",
      "http_method": "POST",
      "http_path": "/",
      "input": {
        "type": "input",
        "members": {
          "old_password": {
            "type": "string",
            "required": true,
            "serialized_name": "OldPassword"
          },
          "new_password": {
            "type": "string",
            "required": true,
            "serialized_name": "NewPassword"
          }
        }
      }
    },
    "create_access_key": {
      "name": "CreateAccessKey",
      "http_method": "POST",
      "http_path": "/",
      "input": {
        "type": "input",
        "members": {
          "user_name": {
            "type": "string",
            "serialized_name": "UserName"
          }
        }
      },
      "output": {
        "type": "output",
        "metadata": {
          "wrapper": "CreateAccessKeyResult"
        },
        "members": {
          "access_key": {
            "type": "structure",
            "serialized_name": "AccessKey",
            "members": {
              "user_name": {
                "type": "string",
                "serialized_name": "UserName"
              },
              "access_key_id": {
                "type": "string",
                "serialized_name": "AccessKeyId"
              },
              "status": {
                "type": "string",
                "serialized_name": "Status",
                "enum": [
                  "Active",
                  "Inactive"
                ]
              },
              "secret_access_key": {
                "type": "string",
                "serialized_name": "SecretAccessKey"
              },
              "create_date": {
                "type": "iso8601_timestamp",
                "serialized_name": "CreateDate"
              }
            }
          }
        }
      }
    },
    "create_account_alias": {
      "name": "CreateAccountAlias",
      "http_method": "POST",
      "http_path": "/",
      "input": {
        "type": "input",
        "members": {
          "account_alias": {
            "type": "string",
            "required": true,
            "serialized_name": "AccountAlias"
          }
        }
      }
    },
    "create_group": {
      "name": "CreateGroup",
      "http_method": "POST",
      "http_path": "/",
      "input": {
        "type": "input",
        "members": {
          "path": {
            "type": "string",
            "serialized_name": "Path"
          },
          "group_name": {
            "type": "string",
            "required": true,
            "serialized_name": "GroupName"
          }
        }
      },
      "output": {
        "type": "output",
        "metadata": {
          "wrapper": "CreateGroupResult"
        },
        "members": {
          "group": {
            "type": "structure",
            "serialized_name": "Group",
            "members": {
              "path": {
                "type": "string",
                "serialized_name": "Path"
              },
              "group_name": {
                "type": "string",
                "serialized_name": "GroupName"
              },
              "group_id": {
                "type": "string",
                "serialized_name": "GroupId"
              },
              "arn": {
                "type": "string",
                "serialized_name": "Arn"
              },
              "create_date": {
                "type": "iso8601_timestamp",
                "serialized_name": "CreateDate"
              }
            }
          }
        }
      }
    },
    "create_instance_profile": {
      "name": "CreateInstanceProfile",
      "http_method": "POST",
      "http_path": "/",
      "input": {
        "type": "input",
        "members": {
          "instance_profile_name": {
            "type": "string",
            "required": true,
            "serialized_name": "InstanceProfileName"
          },
          "path": {
            "type": "string",
            "serialized_name": "Path"
          }
        }
      },
      "output": {
        "type": "output",
        "metadata": {
          "wrapper": "CreateInstanceProfileResult"
        },
        "members": {
          "instance_profile": {
            "type": "structure",
            "serialized_name": "InstanceProfile",
            "members": {
              "path": {
                "type": "string",
                "serialized_name": "Path"
              },
              "instance_profile_name": {
                "type": "string",
                "serialized_name": "InstanceProfileName"
              },
              "instance_profile_id": {
                "type": "string",
                "serialized_name": "InstanceProfileId"
              },
              "arn": {
                "type": "string",
                "serialized_name": "Arn"
              },
              "create_date": {
                "type": "iso8601_timestamp",
                "serialized_name": "CreateDate"
              },
              "roles": {
                "type": "list",
                "serialized_name": "Roles",
                "members": {
                  "type": "structure",
                  "members": {
                    "path": {
                      "type": "string",
                      "serialized_name": "Path"
                    },
                    "role_name": {
                      "type": "string",
                      "serialized_name": "RoleName"
                    },
                    "role_id": {
                      "type": "string",
                      "serialized_name": "RoleId"
                    },
                    "arn": {
                      "type": "string",
                      "serialized_name": "Arn"
                    },
                    "create_date": {
                      "type": "iso8601_timestamp",
                      "serialized_name": "CreateDate"
                    },
                    "assume_role_policy_document": {
                      "type": "string",
                      "serialized_name": "AssumeRolePolicyDocument"
                    }
                  }
                }
              }
            }
          }
        }
      }
    },
    "create_login_profile": {
      "name": "CreateLoginProfile",
      "http_method": "POST",
      "http_path": "/",
      "input": {
        "type": "input",
        "members": {
          "user_name": {
            "type": "string",
            "required": true,
            "serialized_name": "UserName"
          },
          "password": {
            "type": "string",
            "required": true,
            "serialized_name": "Password"
          }
        }
      },
      "output": {
        "type": "output",
        "metadata": {
          "wrapper": "CreateLoginProfileResult"
        },
        "members": {
          "login_profile": {
            "type": "structure",
            "serialized_name": "LoginProfile",
            "members": {
              "user_name": {
                "type": "string",
                "serialized_name": "UserName"
              },
              "create_date": {
                "type": "iso8601_timestamp",
                "serialized_name": "CreateDate"
              }
            }
          }
        }
      }
    },
    "create_role": {
      "name": "CreateRole",
      "http_method": "POST",
      "http_path": "/",
      "input": {
        "type": "input",
        "members": {
          "path": {
            "type": "string",
            "serialized_name": "Path"
          },
          "role_name": {
            "type": "string",
            "required": true,
            "serialized_name": "RoleName"
          },
          "assume_role_policy_document": {
            "type": "string",
            "required": true,
            "serialized_name": "AssumeRolePolicyDocument"
          }
        }
      },
      "output": {
        "type": "output",
        "metadata": {
          "wrapper": "CreateRoleResult"
        },
        "members": {
          "role": {
            "type": "structure",
            "serialized_name": "Role",
            "members": {
              "path": {
                "type": "string",
                "serialized_name": "Path"
              },
              "role_name": {
                "type": "string",
                "serialized_name": "RoleName"
              },
              "role_id": {
                "type": "string",
                "serialized_name": "RoleId"
              },
              "arn": {
                "type": "string",
                "serialized_name": "Arn"
              },
              "create_date": {
                "type": "iso8601_timestamp",
                "serialized_name": "CreateDate"
              },
              "assume_role_policy_document": {
                "type": "string",
                "serialized_name": "AssumeRolePolicyDocument"
              }
            }
          }
        }
      }
    },
    "create_user": {
      "name": "CreateUser",
      "http_method": "POST",
      "http_path": "/",
      "input": {
        "type": "input",
        "members": {
          "path": {
            "type": "string",
            "serialized_name": "Path"
          },
          "user_name": {
            "type": "string",
            "required": true,
            "serialized_name": "UserName"
          }
        }
      },
      "output": {
        "type": "output",
        "metadata": {
          "wrapper": "CreateUserResult"
        },
        "members": {
          "user": {
            "type": "structure",
            "serialized_name": "User",
            "members": {
              "path": {
                "type": "string",
                "serialized_name": "Path"
              },
              "user_name": {
                "type": "string",
                "serialized_name": "UserName"
              },
              "user_id": {
                "type": "string",
                "serialized_name": "UserId"
              },
              "arn": {
                "type": "string",
                "serialized_name": "Arn"
              },
              "create_date": {
                "type": "iso8601_timestamp",
                "serialized_name": "CreateDate"
              }
            }
          }
        }
      }
    },
    "create_virtual_mfa_device": {
      "name": "CreateVirtualMFADevice",
      "http_method": "POST",
      "http_path": "/",
      "input": {
        "type": "input",
        "members": {
          "path": {
            "type": "string",
            "serialized_name": "Path"
          },
          "virtual_mfa_device_name": {
            "type": "string",
            "required": true,
            "serialized_name": "VirtualMFADeviceName"
          }
        }
      },
      "output": {
        "type": "output",
        "metadata": {
          "wrapper": "CreateVirtualMFADeviceResult"
        },
        "members": {
          "virtual_mfa_device": {
            "type": "structure",
            "serialized_name": "VirtualMFADevice",
            "members": {
              "serial_number": {
                "type": "string",
                "serialized_name": "SerialNumber"
              },
              "base_32_string_seed": {
                "type": "blob",
                "serialized_name": "Base32StringSeed"
              },
              "qr_code_png": {
                "type": "blob",
                "serialized_name": "QRCodePNG"
              },
              "user": {
                "type": "structure",
                "serialized_name": "User",
                "members": {
                  "path": {
                    "type": "string",
                    "serialized_name": "Path"
                  },
                  "user_name": {
                    "type": "string",
                    "serialized_name": "UserName"
                  },
                  "user_id": {
                    "type": "string",
                    "serialized_name": "UserId"
                  },
                  "arn": {
                    "type": "string",
                    "serialized_name": "Arn"
                  },
                  "create_date": {
                    "type": "iso8601_timestamp",
                    "serialized_name": "CreateDate"
                  }
                }
              },
              "enable_date": {
                "type": "iso8601_timestamp",
                "serialized_name": "EnableDate"
              }
            }
          }
        }
      }
    },
    "deactivate_mfa_device": {
      "name": "DeactivateMFADevice",
      "http_method": "POST",
      "http_path": "/",
      "input": {
        "type": "input",
        "members": {
          "user_name": {
            "type": "string",
            "required": true,
            "serialized_name": "UserName"
          },
          "serial_number": {
            "type": "string",
            "required": true,
            "serialized_name": "SerialNumber"
          }
        }
      }
    },
    "delete_access_key": {
      "name": "DeleteAccessKey",
      "http_method": "POST",
      "http_path": "/",
      "input": {
        "type": "input",
        "members": {
          "user_name": {
            "type": "string",
            "serialized_name": "UserName"
          },
          "access_key_id": {
            "type": "string",
            "required": true,
            "serialized_name": "AccessKeyId"
          }
        }
      }
    },
    "delete_account_alias": {
      "name": "DeleteAccountAlias",
      "http_method": "POST",
      "http_path": "/",
      "input": {
        "type": "input",
        "members": {
          "account_alias": {
            "type": "string",
            "required": true,
            "serialized_name": "AccountAlias"
          }
        }
      }
    },
    "delete_account_password_policy": {
      "name": "DeleteAccountPasswordPolicy",
      "http_method": "POST",
      "http_path": "/"
    },
    "delete_group": {
      "name": "DeleteGroup",
      "http_method": "POST",
      "http_path": "/",
      "input": {
        "type": "input",
        "members": {
          "group_name": {
            "type": "string",
            "required": true,
            "serialized_name": "GroupName"
          }
        }
      }
    },
    "delete_group_policy": {
      "name": "DeleteGroupPolicy",
      "http_method": "POST",
      "http_path": "/",
      "input": {
        "type": "input",
        "members": {
          "group_name": {
            "type": "string",
            "required": true,
            "serialized_name": "GroupName"
          },
          "policy_name": {
            "type": "string",
            "required": true,
            "serialized_name": "PolicyName"
          }
        }
      }
    },
    "delete_instance_profile": {
      "name": "DeleteInstanceProfile",
      "http_method": "POST",
      "http_path": "/",
      "input": {
        "type": "input",
        "members": {
          "instance_profile_name": {
            "type": "string",
            "required": true,
            "serialized_name": "InstanceProfileName"
          }
        }
      }
    },
    "delete_login_profile": {
      "name": "DeleteLoginProfile",
      "http_method": "POST",
      "http_path": "/",
      "input": {
        "type": "input",
        "members": {
          "user_name": {
            "type": "string",
            "required": true,
            "serialized_name": "UserName"
          }
        }
      }
    },
    "delete_role": {
      "name": "DeleteRole",
      "http_method": "POST",
      "http_path": "/",
      "input": {
        "type": "input",
        "members": {
          "role_name": {
            "type": "string",
            "required": true,
            "serialized_name": "RoleName"
          }
        }
      }
    },
    "delete_role_policy": {
      "name": "DeleteRolePolicy",
      "http_method": "POST",
      "http_path": "/",
      "input": {
        "type": "input",
        "members": {
          "role_name": {
            "type": "string",
            "required": true,
            "serialized_name": "RoleName"
          },
          "policy_name": {
            "type": "string",
            "required": true,
            "serialized_name": "PolicyName"
          }
        }
      }
    },
    "delete_server_certificate": {
      "name": "DeleteServerCertificate",
      "http_method": "POST",
      "http_path": "/",
      "input": {
        "type": "input",
        "members": {
          "server_certificate_name": {
            "type": "string",
            "required": true,
            "serialized_name": "ServerCertificateName"
          }
        }
      }
    },
    "delete_signing_certificate": {
      "name": "DeleteSigningCertificate",
      "http_method": "POST",
      "http_path": "/",
      "input": {
        "type": "input",
        "members": {
          "user_name": {
            "type": "string",
            "serialized_name": "UserName"
          },
          "certificate_id": {
            "type": "string",
            "required": true,
            "serialized_name": "CertificateId"
          }
        }
      }
    },
    "delete_user": {
      "name": "DeleteUser",
      "http_method": "POST",
      "http_path": "/",
      "input": {
        "type": "input",
        "members": {
          "user_name": {
            "type": "string",
            "required": true,
            "serialized_name": "UserName"
          }
        }
      }
    },
    "delete_user_policy": {
      "name": "DeleteUserPolicy",
      "http_method": "POST",
      "http_path": "/",
      "input": {
        "type": "input",
        "members": {
          "user_name": {
            "type": "string",
            "required": true,
            "serialized_name": "UserName"
          },
          "policy_name": {
            "type": "string",
            "required": true,
            "serialized_name": "PolicyName"
          }
        }
      }
    },
    "delete_virtual_mfa_device": {
      "name": "DeleteVirtualMFADevice",
      "http_method": "POST",
      "http_path": "/",
      "input": {
        "type": "input",
        "members": {
          "serial_number": {
            "type": "string",
            "required": true,
            "serialized_name": "SerialNumber"
          }
        }
      }
    },
    "enable_mfa_device": {
      "name": "EnableMFADevice",
      "http_method": "POST",
      "http_path": "/",
      "input": {
        "type": "input",
        "members": {
          "user_name": {
            "type": "string",
            "required": true,
            "serialized_name": "UserName"
          },
          "serial_number": {
            "type": "string",
            "required": true,
            "serialized_name": "SerialNumber"
          },
          "authentication_code_1": {
            "type": "string",
            "required": true,
            "serialized_name": "AuthenticationCode1"
          },
          "authentication_code_2": {
            "type": "string",
            "required": true,
            "serialized_name": "AuthenticationCode2"
          }
        }
      }
    },
    "get_account_password_policy": {
      "name": "GetAccountPasswordPolicy",
      "http_method": "POST",
      "http_path": "/",
      "output": {
        "type": "output",
        "metadata": {
          "wrapper": "GetAccountPasswordPolicyResult"
        },
        "members": {
          "password_policy": {
            "type": "structure",
            "serialized_name": "PasswordPolicy",
            "members": {
              "minimum_password_length": {
                "type": "integer",
                "serialized_name": "MinimumPasswordLength"
              },
              "require_symbols": {
                "type": "boolean",
                "serialized_name": "RequireSymbols"
              },
              "require_numbers": {
                "type": "boolean",
                "serialized_name": "RequireNumbers"
              },
              "require_uppercase_characters": {
                "type": "boolean",
                "serialized_name": "RequireUppercaseCharacters"
              },
              "require_lowercase_characters": {
                "type": "boolean",
                "serialized_name": "RequireLowercaseCharacters"
              },
              "allow_users_to_change_password": {
                "type": "boolean",
                "serialized_name": "AllowUsersToChangePassword"
              }
            }
          }
        }
      }
    },
    "get_account_summary": {
      "name": "GetAccountSummary",
      "http_method": "POST",
      "http_path": "/",
      "output": {
        "type": "output",
        "metadata": {
          "wrapper": "GetAccountSummaryResult"
        },
        "members": {
          "summary_map": {
            "type": "map",
            "serialized_name": "SummaryMap",
            "keys": {
              "type": "string",
              "enum": [
                "Users",
                "UsersQuota",
                "Groups",
                "GroupsQuota",
                "ServerCertificates",
                "ServerCertificatesQuota",
                "UserPolicySizeQuota",
                "GroupPolicySizeQuota",
                "GroupsPerUserQuota",
                "SigningCertificatesPerUserQuota",
                "AccessKeysPerUserQuota",
                "MFADevices",
                "MFADevicesInUse",
                "AccountMFAEnabled"
              ]
            },
            "members": {
              "type": "integer"
            }
          }
        }
      }
    },
    "get_group": {
      "name": "GetGroup",
      "http_method": "POST",
      "http_path": "/",
      "input": {
        "type": "input",
        "members": {
          "group_name": {
            "type": "string",
            "required": true,
            "serialized_name": "GroupName"
          },
          "marker": {
            "type": "string",
            "serialized_name": "Marker"
          },
          "max_items": {
            "type": "integer",
            "serialized_name": "MaxItems"
          }
        }
      },
      "output": {
        "type": "output",
        "metadata": {
          "wrapper": "GetGroupResult"
        },
        "members": {
          "group": {
            "type": "structure",
            "serialized_name": "Group",
            "members": {
              "path": {
                "type": "string",
                "serialized_name": "Path"
              },
              "group_name": {
                "type": "string",
                "serialized_name": "GroupName"
              },
              "group_id": {
                "type": "string",
                "serialized_name": "GroupId"
              },
              "arn": {
                "type": "string",
                "serialized_name": "Arn"
              },
              "create_date": {
                "type": "iso8601_timestamp",
                "serialized_name": "CreateDate"
              }
            }
          },
          "users": {
            "type": "list",
            "serialized_name": "Users",
            "members": {
              "type": "structure",
              "members": {
                "path": {
                  "type": "string",
                  "serialized_name": "Path"
                },
                "user_name": {
                  "type": "string",
                  "serialized_name": "UserName"
                },
                "user_id": {
                  "type": "string",
                  "serialized_name": "UserId"
                },
                "arn": {
                  "type": "string",
                  "serialized_name": "Arn"
                },
                "create_date": {
                  "type": "iso8601_timestamp",
                  "serialized_name": "CreateDate"
                }
              }
            }
          },
          "is_truncated": {
            "type": "boolean",
            "serialized_name": "IsTruncated"
          },
          "marker": {
            "type": "string",
            "serialized_name": "Marker"
          }
        }
      }
    },
    "get_group_policy": {
      "name": "GetGroupPolicy",
      "http_method": "POST",
      "http_path": "/",
      "input": {
        "type": "input",
        "members": {
          "group_name": {
            "type": "string",
            "required": true,
            "serialized_name": "GroupName"
          },
          "policy_name": {
            "type": "string",
            "required": true,
            "serialized_name": "PolicyName"
          }
        }
      },
      "output": {
        "type": "output",
        "metadata": {
          "wrapper": "GetGroupPolicyResult"
        },
        "members": {
          "group_name": {
            "type": "string",
            "serialized_name": "GroupName"
          },
          "policy_name": {
            "type": "string",
            "serialized_name": "PolicyName"
          },
          "policy_document": {
            "type": "string",
            "serialized_name": "PolicyDocument"
          }
        }
      }
    },
    "get_instance_profile": {
      "name": "GetInstanceProfile",
      "http_method": "POST",
      "http_path": "/",
      "input": {
        "type": "input",
        "members": {
          "instance_profile_name": {
            "type": "string",
            "required": true,
            "serialized_name": "InstanceProfileName"
          }
        }
      },
      "output": {
        "type": "output",
        "metadata": {
          "wrapper": "GetInstanceProfileResult"
        },
        "members": {
          "instance_profile": {
            "type": "structure",
            "serialized_name": "InstanceProfile",
            "members": {
              "path": {
                "type": "string",
                "serialized_name": "Path"
              },
              "instance_profile_name": {
                "type": "string",
                "serialized_name": "InstanceProfileName"
              },
              "instance_profile_id": {
                "type": "string",
                "serialized_name": "InstanceProfileId"
              },
              "arn": {
                "type": "string",
                "serialized_name": "Arn"
              },
              "create_date": {
                "type": "iso8601_timestamp",
                "serialized_name": "CreateDate"
              },
              "roles": {
                "type": "list",
                "serialized_name": "Roles",
                "members": {
                  "type": "structure",
                  "members": {
                    "path": {
                      "type": "string",
                      "serialized_name": "Path"
                    },
                    "role_name": {
                      "type": "string",
                      "serialized_name": "RoleName"
                    },
                    "role_id": {
                      "type": "string",
                      "serialized_name": "RoleId"
                    },
                    "arn": {
                      "type": "string",
                      "serialized_name": "Arn"
                    },
                    "create_date": {
                      "type": "iso8601_timestamp",
                      "serialized_name": "CreateDate"
                    },
                    "assume_role_policy_document": {
                      "type": "string",
                      "serialized_name": "AssumeRolePolicyDocument"
                    }
                  }
                }
              }
            }
          }
        }
      }
    },
    "get_login_profile": {
      "name": "GetLoginProfile",
      "http_method": "POST",
      "http_path": "/",
      "input": {
        "type": "input",
        "members": {
          "user_name": {
            "type": "string",
            "required": true,
            "serialized_name": "UserName"
          }
        }
      },
      "output": {
        "type": "output",
        "metadata": {
          "wrapper": "GetLoginProfileResult"
        },
        "members": {
          "login_profile": {
            "type": "structure",
            "serialized_name": "LoginProfile",
            "members": {
              "user_name": {
                "type": "string",
                "serialized_name": "UserName"
              },
              "create_date": {
                "type": "iso8601_timestamp",
                "serialized_name": "CreateDate"
              }
            }
          }
        }
      }
    },
    "get_role": {
      "name": "GetRole",
      "http_method": "POST",
      "http_path": "/",
      "input": {
        "type": "input",
        "members": {
          "role_name": {
            "type": "string",
            "required": true,
            "serialized_name": "RoleName"
          }
        }
      },
      "output": {
        "type": "output",
        "metadata": {
          "wrapper": "GetRoleResult"
        },
        "members": {
          "role": {
            "type": "structure",
            "serialized_name": "Role",
            "members": {
              "path": {
                "type": "string",
                "serialized_name": "Path"
              },
              "role_name": {
                "type": "string",
                "serialized_name": "RoleName"
              },
              "role_id": {
                "type": "string",
                "serialized_name": "RoleId"
              },
              "arn": {
                "type": "string",
                "serialized_name": "Arn"
              },
              "create_date": {
                "type": "iso8601_timestamp",
                "serialized_name": "CreateDate"
              },
              "assume_role_policy_document": {
                "type": "string",
                "serialized_name": "AssumeRolePolicyDocument"
              }
            }
          }
        }
      }
    },
    "get_role_policy": {
      "name": "GetRolePolicy",
      "http_method": "POST",
      "http_path": "/",
      "input": {
        "type": "input",
        "members": {
          "role_name": {
            "type": "string",
            "required": true,
            "serialized_name": "RoleName"
          },
          "policy_name": {
            "type": "string",
            "required": true,
            "serialized_name": "PolicyName"
          }
        }
      },
      "output": {
        "type": "output",
        "metadata": {
          "wrapper": "GetRolePolicyResult"
        },
        "members": {
          "role_name": {
            "type": "string",
            "serialized_name": "RoleName"
          },
          "policy_name": {
            "type": "string",
            "serialized_name": "PolicyName"
          },
          "policy_document": {
            "type": "string",
            "serialized_name": "PolicyDocument"
          }
        }
      }
    },
    "get_server_certificate": {
      "name": "GetServerCertificate",
      "http_method": "POST",
      "http_path": "/",
      "input": {
        "type": "input",
        "members": {
          "server_certificate_name": {
            "type": "string",
            "required": true,
            "serialized_name": "ServerCertificateName"
          }
        }
      },
      "output": {
        "type": "output",
        "metadata": {
          "wrapper": "GetServerCertificateResult"
        },
        "members": {
          "server_certificate": {
            "type": "structure",
            "serialized_name": "ServerCertificate",
            "members": {
              "server_certificate_metadata": {
                "type": "structure",
                "serialized_name": "ServerCertificateMetadata",
                "members": {
                  "path": {
                    "type": "string",
                    "serialized_name": "Path"
                  },
                  "server_certificate_name": {
                    "type": "string",
                    "serialized_name": "ServerCertificateName"
                  },
                  "server_certificate_id": {
                    "type": "string",
                    "serialized_name": "ServerCertificateId"
                  },
                  "arn": {
                    "type": "string",
                    "serialized_name": "Arn"
                  },
                  "upload_date": {
                    "type": "iso8601_timestamp",
                    "serialized_name": "UploadDate"
                  }
                }
              },
              "certificate_body": {
                "type": "string",
                "serialized_name": "CertificateBody"
              },
              "certificate_chain": {
                "type": "string",
                "serialized_name": "CertificateChain"
              }
            }
          }
        }
      }
    },
    "get_user": {
      "name": "GetUser",
      "http_method": "POST",
      "http_path": "/",
      "input": {
        "type": "input",
        "members": {
          "user_name": {
            "type": "string",
            "serialized_name": "UserName"
          }
        }
      },
      "output": {
        "type": "output",
        "metadata": {
          "wrapper": "GetUserResult"
        },
        "members": {
          "user": {
            "type": "structure",
            "serialized_name": "User",
            "members": {
              "path": {
                "type": "string",
                "serialized_name": "Path"
              },
              "user_name": {
                "type": "string",
                "serialized_name": "UserName"
              },
              "user_id": {
                "type": "string",
                "serialized_name": "UserId"
              },
              "arn": {
                "type": "string",
                "serialized_name": "Arn"
              },
              "create_date": {
                "type": "iso8601_timestamp",
                "serialized_name": "CreateDate"
              }
            }
          }
        }
      }
    },
    "get_user_policy": {
      "name": "GetUserPolicy",
      "http_method": "POST",
      "http_path": "/",
      "input": {
        "type": "input",
        "members": {
          "user_name": {
            "type": "string",
            "required": true,
            "serialized_name": "UserName"
          },
          "policy_name": {
            "type": "string",
            "required": true,
            "serialized_name": "PolicyName"
          }
        }
      },
      "output": {
        "type": "output",
        "metadata": {
          "wrapper": "GetUserPolicyResult"
        },
        "members": {
          "user_name": {
            "type": "string",
            "serialized_name": "UserName"
          },
          "policy_name": {
            "type": "string",
            "serialized_name": "PolicyName"
          },
          "policy_document": {
            "type": "string",
            "serialized_name": "PolicyDocument"
          }
        }
      }
    },
    "list_access_keys": {
      "name": "ListAccessKeys",
      "http_method": "POST",
      "http_path": "/",
      "input": {
        "type": "input",
        "members": {
          "user_name": {
            "type": "string",
            "serialized_name": "UserName"
          },
          "marker": {
            "type": "string",
            "serialized_name": "Marker"
          },
          "max_items": {
            "type": "integer",
            "serialized_name": "MaxItems"
          }
        }
      },
      "output": {
        "type": "output",
        "metadata": {
          "wrapper": "ListAccessKeysResult"
        },
        "members": {
          "access_key_metadata": {
            "type": "list",
            "serialized_name": "AccessKeyMetadata",
            "members": {
              "type": "structure",
              "members": {
                "user_name": {
                  "type": "string",
                  "serialized_name": "UserName"
                },
                "access_key_id": {
                  "type": "string",
                  "serialized_name": "AccessKeyId"
                },
                "status": {
                  "type": "string",
                  "serialized_name": "Status",
                  "enum": [
                    "Active",
                    "Inactive"
                  ]
                },
                "create_date": {
                  "type": "iso8601_timestamp",
                  "serialized_name": "CreateDate"
                }
              }
            }
          },
          "is_truncated": {
            "type": "boolean",
            "serialized_name": "IsTruncated"
          },
          "marker": {
            "type": "string",
            "serialized_name": "Marker"
          }
        }
      }
    },
    "list_account_aliases": {
      "name": "ListAccountAliases",
      "http_method": "POST",
      "http_path": "/",
      "input": {
        "type": "input",
        "members": {
          "marker": {
            "type": "string",
            "serialized_name": "Marker"
          },
          "max_items": {
            "type": "integer",
            "serialized_name": "MaxItems"
          }
        }
      },
      "output": {
        "type": "output",
        "metadata": {
          "wrapper": "ListAccountAliasesResult"
        },
        "members": {
          "account_aliases": {
            "type": "list",
            "serialized_name": "AccountAliases",
            "members": {
              "type": "string"
            }
          },
          "is_truncated": {
            "type": "boolean",
            "serialized_name": "IsTruncated"
          },
          "marker": {
            "type": "string",
            "serialized_name": "Marker"
          }
        }
      }
    },
    "list_group_policies": {
      "name": "ListGroupPolicies",
      "http_method": "POST",
      "http_path": "/",
      "input": {
        "type": "input",
        "members": {
          "group_name": {
            "type": "string",
            "required": true,
            "serialized_name": "GroupName"
          },
          "marker": {
            "type": "string",
            "serialized_name": "Marker"
          },
          "max_items": {
            "type": "integer",
            "serialized_name": "MaxItems"
          }
        }
      },
      "output": {
        "type": "output",
        "metadata": {
          "wrapper": "ListGroupPoliciesResult"
        },
        "members": {
          "policy_names": {
            "type": "list",
            "serialized_name": "PolicyNames",
            "members": {
              "type": "string"
            }
          },
          "is_truncated": {
            "type": "boolean",
            "serialized_name": "IsTruncated"
          },
          "marker": {
            "type": "string",
            "serialized_name": "Marker"
          }
        }
      }
    },
    "list_groups": {
      "name": "ListGroups",
      "http_method": "POST",
      "http_path": "/",
      "input": {
        "type": "input",
        "members": {
          "path_prefix": {
            "type": "string",
            "serialized_name": "PathPrefix"
          },
          "marker": {
            "type": "string",
            "serialized_name": "Marker"
          },
          "max_items": {
            "type": "integer",
            "serialized_name": "MaxItems"
          }
        }
      },
      "output": {
        "type": "output",
        "metadata": {
          "wrapper": "ListGroupsResult"
        },
        "members": {
          "groups": {
            "type": "list",
            "serialized_name": "Groups",
            "members": {
              "type": "structure",
              "members": {
                "path": {
                  "type": "string",
                  "serialized_name": "Path"
                },
                "group_name": {
                  "type": "string",
                  "serialized_name": "GroupName"
                },
                "group_id": {
                  "type": "string",
                  "serialized_name": "GroupId"
                },
                "arn": {
                  "type": "string",
                  "serialized_name": "Arn"
                },
                "create_date": {
                  "type": "iso8601_timestamp",
                  "serialized_name": "CreateDate"
                }
              }
            }
          },
          "is_truncated": {
            "type": "boolean",
            "serialized_name": "IsTruncated"
          },
          "marker": {
            "type": "string",
            "serialized_name": "Marker"
          }
        }
      }
    },
    "list_groups_for_user": {
      "name": "ListGroupsForUser",
      "http_method": "POST",
      "http_path": "/",
      "input": {
        "type": "input",
        "members": {
          "user_name": {
            "type": "string",
            "required": true,
            "serialized_name": "UserName"
          },
          "marker": {
            "type": "string",
            "serialized_name": "Marker"
          },
          "max_items": {
            "type": "integer",
            "serialized_name": "MaxItems"
          }
        }
      },
      "output": {
        "type": "output",
        "metadata": {
          "wrapper": "ListGroupsForUserResult"
        },
        "members": {
          "groups": {
            "type": "list",
            "serialized_name": "Groups",
            "members": {
              "type": "structure",
              "members": {
                "path": {
                  "type": "string",
                  "serialized_name": "Path"
                },
                "group_name": {
                  "type": "string",
                  "serialized_name": "GroupName"
                },
                "group_id": {
                  "type": "string",
                  "serialized_name": "GroupId"
                },
                "arn": {
                  "type": "string",
                  "serialized_name": "Arn"
                },
                "create_date": {
                  "type": "iso8601_timestamp",
                  "serialized_name": "CreateDate"
                }
              }
            }
          },
          "is_truncated": {
            "type": "boolean",
            "serialized_name": "IsTruncated"
          },
          "marker": {
            "type": "string",
            "serialized_name": "Marker"
          }
        }
      }
    },
    "list_instance_profiles": {
      "name": "ListInstanceProfiles",
      "http_method": "POST",
      "http_path": "/",
      "input": {
        "type": "input",
        "members": {
          "path_prefix": {
            "type": "string",
            "serialized_name": "PathPrefix"
          },
          "marker": {
            "type": "string",
            "serialized_name": "Marker"
          },
          "max_items": {
            "type": "integer",
            "serialized_name": "MaxItems"
          }
        }
      },
      "output": {
        "type": "output",
        "metadata": {
          "wrapper": "ListInstanceProfilesResult"
        },
        "members": {
          "instance_profiles": {
            "type": "list",
            "serialized_name": "InstanceProfiles",
            "members": {
              "type": "structure",
              "members": {
                "path": {
                  "type": "string",
                  "serialized_name": "Path"
                },
                "instance_profile_name": {
                  "type": "string",
                  "serialized_name": "InstanceProfileName"
                },
                "instance_profile_id": {
                  "type": "string",
                  "serialized_name": "InstanceProfileId"
                },
                "arn": {
                  "type": "string",
                  "serialized_name": "Arn"
                },
                "create_date": {
                  "type": "iso8601_timestamp",
                  "serialized_name": "CreateDate"
                },
                "roles": {
                  "type": "list",
                  "serialized_name": "Roles",
                  "members": {
                    "type": "structure",
                    "members": {
                      "path": {
                        "type": "string",
                        "serialized_name": "Path"
                      },
                      "role_name": {
                        "type": "string",
                        "serialized_name": "RoleName"
                      },
                      "role_id": {
                        "type": "string",
                        "serialized_name": "RoleId"
                      },
                      "arn": {
                        "type": "string",
                        "serialized_name": "Arn"
                      },
                      "create_date": {
                        "type": "iso8601_timestamp",
                        "serialized_name": "CreateDate"
                      },
                      "assume_role_policy_document": {
                        "type": "string",
                        "serialized_name": "AssumeRolePolicyDocument"
                      }
                    }
                  }
                }
              }
            }
          },
          "is_truncated": {
            "type": "boolean",
            "serialized_name": "IsTruncated"
          },
          "marker": {
            "type": "string",
            "serialized_name": "Marker"
          }
        }
      }
    },
    "list_instance_profiles_for_role": {
      "name": "ListInstanceProfilesForRole",
      "http_method": "POST",
      "http_path": "/",
      "input": {
        "type": "input",
        "members": {
          "role_name": {
            "type": "string",
            "required": true,
            "serialized_name": "RoleName"
          },
          "marker": {
            "type": "string",
            "serialized_name": "Marker"
          },
          "max_items": {
            "type": "integer",
            "serialized_name": "MaxItems"
          }
        }
      },
      "output": {
        "type": "output",
        "metadata": {
          "wrapper": "ListInstanceProfilesForRoleResult"
        },
        "members": {
          "instance_profiles": {
            "type": "list",
            "serialized_name": "InstanceProfiles",
            "members": {
              "type": "structure",
              "members": {
                "path": {
                  "type": "string",
                  "serialized_name": "Path"
                },
                "instance_profile_name": {
                  "type": "string",
                  "serialized_name": "InstanceProfileName"
                },
                "instance_profile_id": {
                  "type": "string",
                  "serialized_name": "InstanceProfileId"
                },
                "arn": {
                  "type": "string",
                  "serialized_name": "Arn"
                },
                "create_date": {
                  "type": "iso8601_timestamp",
                  "serialized_name": "CreateDate"
                },
                "roles": {
                  "type": "list",
                  "serialized_name": "Roles",
                  "members": {
                    "type": "structure",
                    "members": {
                      "path": {
                        "type": "string",
                        "serialized_name": "Path"
                      },
                      "role_name": {
                        "type": "string",
                        "serialized_name": "RoleName"
                      },
                      "role_id": {
                        "type": "string",
                        "serialized_name": "RoleId"
                      },
                      "arn": {
                        "type": "string",
                        "serialized_name": "Arn"
                      },
                      "create_date": {
                        "type": "iso8601_timestamp",
                        "serialized_name": "CreateDate"
                      },
                      "assume_role_policy_document": {
                        "type": "string",
                        "serialized_name": "AssumeRolePolicyDocument"
                      }
                    }
                  }
                }
              }
            }
          },
          "is_truncated": {
            "type": "boolean",
            "serialized_name": "IsTruncated"
          },
          "marker": {
            "type": "string",
            "serialized_name": "Marker"
          }
        }
      }
    },
    "list_mfa_devices": {
      "name": "ListMFADevices",
      "http_method": "POST",
      "http_path": "/",
      "input": {
        "type": "input",
        "members": {
          "user_name": {
            "type": "string",
            "serialized_name": "UserName"
          },
          "marker": {
            "type": "string",
            "serialized_name": "Marker"
          },
          "max_items": {
            "type": "integer",
            "serialized_name": "MaxItems"
          }
        }
      },
      "output": {
        "type": "output",
        "metadata": {
          "wrapper": "ListMFADevicesResult"
        },
        "members": {
          "mfa_devices": {
            "type": "list",
            "serialized_name": "MFADevices",
            "members": {
              "type": "structure",
              "members": {
                "user_name": {
                  "type": "string",
                  "serialized_name": "UserName"
                },
                "serial_number": {
                  "type": "string",
                  "serialized_name": "SerialNumber"
                },
                "enable_date": {
                  "type": "iso8601_timestamp",
                  "serialized_name": "EnableDate"
                }
              }
            }
          },
          "is_truncated": {
            "type": "boolean",
            "serialized_name": "IsTruncated"
          },
          "marker": {
            "type": "string",
            "serialized_name": "Marker"
          }
        }
      }
    },
    "list_role_policies": {
      "name": "ListRolePolicies",
      "http_method": "POST",
      "http_path": "/",
      "input": {
        "type": "input",
        "members": {
          "role_name": {
            "type": "string",
            "required": true,
            "serialized_name": "RoleName"
          },
          "marker": {
            "type": "string",
            "serialized_name": "Marker"
          },
          "max_items": {
            "type": "integer",
            "serialized_name": "MaxItems"
          }
        }
      },
      "output": {
        "type": "output",
        "metadata": {
          "wrapper": "ListRolePoliciesResult"
        },
        "members": {
          "policy_names": {
            "type": "list",
            "serialized_name": "PolicyNames",
            "members": {
              "type": "string"
            }
          },
          "is_truncated": {
            "type": "boolean",
            "serialized_name": "IsTruncated"
          },
          "marker": {
            "type": "string",
            "serialized_name": "Marker"
          }
        }
      }
    },
    "list_roles": {
      "name": "ListRoles",
      "http_method": "POST",
      "http_path": "/",
      "input": {
        "type": "input",
        "members": {
          "path_prefix": {
            "type": "string",
            "serialized_name": "PathPrefix"
          },
          "marker": {
            "type": "string",
            "serialized_name": "Marker"
          },
          "max_items": {
            "type": "integer",
            "serialized_name": "MaxItems"
          }
        }
      },
      "output": {
        "type": "output",
        "metadata": {
          "wrapper": "ListRolesResult"
        },
        "members": {
          "roles": {
            "type": "list",
            "serialized_name": "Roles",
            "members": {
              "type": "structure",
              "members": {
                "path": {
                  "type": "string",
                  "serialized_name": "Path"
                },
                "role_name": {
                  "type": "string",
                  "serialized_name": "RoleName"
                },
                "role_id": {
                  "type": "string",
                  "serialized_name": "RoleId"
                },
                "arn": {
                  "type": "string",
                  "serialized_name": "Arn"
                },
                "create_date": {
                  "type": "iso8601_timestamp",
                  "serialized_name": "CreateDate"
                },
                "assume_role_policy_document": {
                  "type": "string",
                  "serialized_name": "AssumeRolePolicyDocument"
                }
              }
            }
          },
          "is_truncated": {
            "type": "boolean",
            "serialized_name": "IsTruncated"
          },
          "marker": {
            "type": "string",
            "serialized_name": "Marker"
          }
        }
      }
    },
    "list_server_certificates": {
      "name": "ListServerCertificates",
      "http_method": "POST",
      "http_path": "/",
      "input": {
        "type": "input",
        "members": {
          "path_prefix": {
            "type": "string",
            "serialized_name": "PathPrefix"
          },
          "marker": {
            "type": "string",
            "serialized_name": "Marker"
          },
          "max_items": {
            "type": "integer",
            "serialized_name": "MaxItems"
          }
        }
      },
      "output": {
        "type": "output",
        "metadata": {
          "wrapper": "ListServerCertificatesResult"
        },
        "members": {
          "server_certificate_metadata_list": {
            "type": "list",
            "serialized_name": "ServerCertificateMetadataList",
            "members": {
              "type": "structure",
              "members": {
                "path": {
                  "type": "string",
                  "serialized_name": "Path"
                },
                "server_certificate_name": {
                  "type": "string",
                  "serialized_name": "ServerCertificateName"
                },
                "server_certificate_id": {
                  "type": "string",
                  "serialized_name": "ServerCertificateId"
                },
                "arn": {
                  "type": "string",
                  "serialized_name": "Arn"
                },
                "upload_date": {
                  "type": "iso8601_timestamp",
                  "serialized_name": "UploadDate"
                }
              }
            }
          },
          "is_truncated": {
            "type": "boolean",
            "serialized_name": "IsTruncated"
          },
          "marker": {
            "type": "string",
            "serialized_name": "Marker"
          }
        }
      }
    },
    "list_signing_certificates": {
      "name": "ListSigningCertificates",
      "http_method": "POST",
      "http_path": "/",
      "input": {
        "type": "input",
        "members": {
          "user_name": {
            "type": "string",
            "serialized_name": "UserName"
          },
          "marker": {
            "type": "string",
            "serialized_name": "Marker"
          },
          "max_items": {
            "type": "integer",
            "serialized_name": "MaxItems"
          }
        }
      },
      "output": {
        "type": "output",
        "metadata": {
          "wrapper": "ListSigningCertificatesResult"
        },
        "members": {
          "certificates": {
            "type": "list",
            "serialized_name": "Certificates",
            "members": {
              "type": "structure",
              "members": {
                "user_name": {
                  "type": "string",
                  "serialized_name": "UserName"
                },
                "certificate_id": {
                  "type": "string",
                  "serialized_name": "CertificateId"
                },
                "certificate_body": {
                  "type": "string",
                  "serialized_name": "CertificateBody"
                },
                "status": {
                  "type": "string",
                  "serialized_name": "Status",
                  "enum": [
                    "Active",
                    "Inactive"
                  ]
                },
                "upload_date": {
                  "type": "iso8601_timestamp",
                  "serialized_name": "UploadDate"
                }
              }
            }
          },
          "is_truncated": {
            "type": "boolean",
            "serialized_name": "IsTruncated"
          },
          "marker": {
            "type": "string",
            "serialized_name": "Marker"
          }
        }
      }
    },
    "list_user_policies": {
      "name": "ListUserPolicies",
      "http_method": "POST",
      "http_path": "/",
      "input": {
        "type": "input",
        "members": {
          "user_name": {
            "type": "string",
            "required": true,
            "serialized_name": "UserName"
          },
          "marker": {
            "type": "string",
            "serialized_name": "Marker"
          },
          "max_items": {
            "type": "integer",
            "serialized_name": "MaxItems"
          }
        }
      },
      "output": {
        "type": "output",
        "metadata": {
          "wrapper": "ListUserPoliciesResult"
        },
        "members": {
          "policy_names": {
            "type": "list",
            "serialized_name": "PolicyNames",
            "members": {
              "type": "string"
            }
          },
          "is_truncated": {
            "type": "boolean",
            "serialized_name": "IsTruncated"
          },
          "marker": {
            "type": "string",
            "serialized_name": "Marker"
          }
        }
      }
    },
    "list_users": {
      "name": "ListUsers",
      "http_method": "POST",
      "http_path": "/",
      "input": {
        "type": "input",
        "members": {
          "path_prefix": {
            "type": "string",
            "serialized_name": "PathPrefix"
          },
          "marker": {
            "type": "string",
            "serialized_name": "Marker"
          },
          "max_items": {
            "type": "integer",
            "serialized_name": "MaxItems"
          }
        }
      },
      "output": {
        "type": "output",
        "metadata": {
          "wrapper": "ListUsersResult"
        },
        "members": {
          "users": {
            "type": "list",
            "serialized_name": "Users",
            "members": {
              "type": "structure",
              "members": {
                "path": {
                  "type": "string",
                  "serialized_name": "Path"
                },
                "user_name": {
                  "type": "string",
                  "serialized_name": "UserName"
                },
                "user_id": {
                  "type": "string",
                  "serialized_name": "UserId"
                },
                "arn": {
                  "type": "string",
                  "serialized_name": "Arn"
                },
                "create_date": {
                  "type": "iso8601_timestamp",
                  "serialized_name": "CreateDate"
                }
              }
            }
          },
          "is_truncated": {
            "type": "boolean",
            "serialized_name": "IsTruncated"
          },
          "marker": {
            "type": "string",
            "serialized_name": "Marker"
          }
        }
      }
    },
    "list_virtual_mfa_devices": {
      "name": "ListVirtualMFADevices",
      "http_method": "POST",
      "http_path": "/",
      "input": {
        "type": "input",
        "members": {
          "assignment_status": {
            "type": "string",
            "serialized_name": "AssignmentStatus",
            "enum": [
              "Assigned",
              "Unassigned",
              "Any"
            ]
          },
          "marker": {
            "type": "string",
            "serialized_name": "Marker"
          },
          "max_items": {
            "type": "integer",
            "serialized_name": "MaxItems"
          }
        }
      },
      "output": {
        "type": "output",
        "metadata": {
          "wrapper": "ListVirtualMFADevicesResult"
        },
        "members": {
          "virtual_mfa_devices": {
            "type": "list",
            "serialized_name": "VirtualMFADevices",
            "members": {
              "type": "structure",
              "members": {
                "serial_number": {
                  "type": "string",
                  "serialized_name": "SerialNumber"
                },
                "base_32_string_seed": {
                  "type": "blob",
                  "serialized_name": "Base32StringSeed"
                },
                "qr_code_png": {
                  "type": "blob",
                  "serialized_name": "QRCodePNG"
                },
                "user": {
                  "type": "structure",
                  "serialized_name": "User",
                  "members": {
                    "path": {
                      "type": "string",
                      "serialized_name": "Path"
                    },
                    "user_name": {
                      "type": "string",
                      "serialized_name": "UserName"
                    },
                    "user_id": {
                      "type": "string",
                      "serialized_name": "UserId"
                    },
                    "arn": {
                      "type": "string",
                      "serialized_name": "Arn"
                    },
                    "create_date": {
                      "type": "iso8601_timestamp",
                      "serialized_name": "CreateDate"
                    }
                  }
                },
                "enable_date": {
                  "type": "iso8601_timestamp",
                  "serialized_name": "EnableDate"
                }
              }
            }
          },
          "is_truncated": {
            "type": "boolean",
            "serialized_name": "IsTruncated"
          },
          "marker": {
            "type": "string",
            "serialized_name": "Marker"
          }
        }
      }
    },
    "put_group_policy": {
      "name": "PutGroupPolicy",
      "http_method": "POST",
      "http_path": "/",
      "input": {
        "type": "input",
        "members": {
          "group_name": {
            "type": "string",
            "required": true,
            "serialized_name": "GroupName"
          },
          "policy_name": {
            "type": "string",
            "required": true,
            "serialized_name": "PolicyName"
          },
          "policy_document": {
            "type": "string",
            "required": true,
            "serialized_name": "PolicyDocument"
          }
        }
      }
    },
    "put_role_policy": {
      "name": "PutRolePolicy",
      "http_method": "POST",
      "http_path": "/",
      "input": {
        "type": "input",
        "members": {
          "role_name": {
            "type": "string",
            "required": true,
            "serialized_name": "RoleName"
          },
          "policy_name": {
            "type": "string",
            "required": true,
            "serialized_name": "PolicyName"
          },
          "policy_document": {
            "type": "string",
            "required": true,
            "serialized_name": "PolicyDocument"
          }
        }
      }
    },
    "put_user_policy": {
      "name": "PutUserPolicy",
      "http_method": "POST",
      "http_path": "/",
      "input": {
        "type": "input",
        "members": {
          "user_name": {
            "type": "string",
            "required": true,
            "serialized_name": "UserName"
          },
          "policy_name": {
            "type": "string",
            "required": true,
            "serialized_name": "PolicyName"
          },
          "policy_document": {
            "type": "string",
            "required": true,
            "serialized_name": "PolicyDocument"
          }
        }
      }
    },
    "remove_role_from_instance_profile": {
      "name": "RemoveRoleFromInstanceProfile",
      "http_method": "POST",
      "http_path": "/",
      "input": {
        "type": "input",
        "members": {
          "instance_profile_name": {
            "type": "string",
            "required": true,
            "serialized_name": "InstanceProfileName"
          },
          "role_name": {
            "type": "string",
            "required": true,
            "serialized_name": "RoleName"
          }
        }
      }
    },
    "remove_user_from_group": {
      "name": "RemoveUserFromGroup",
      "http_method": "POST",
      "http_path": "/",
      "input": {
        "type": "input",
        "members": {
          "group_name": {
            "type": "string",
            "required": true,
            "serialized_name": "GroupName"
          },
          "user_name": {
            "type": "string",
            "required": true,
            "serialized_name": "UserName"
          }
        }
      }
    },
    "resync_mfa_device": {
      "name": "ResyncMFADevice",
      "http_method": "POST",
      "http_path": "/",
      "input": {
        "type": "input",
        "members": {
          "user_name": {
            "type": "string",
            "required": true,
            "serialized_name": "UserName"
          },
          "serial_number": {
            "type": "string",
            "required": true,
            "serialized_name": "SerialNumber"
          },
          "authentication_code_1": {
            "type": "string",
            "required": true,
            "serialized_name": "AuthenticationCode1"
          },
          "authentication_code_2": {
            "type": "string",
            "required": true,
            "serialized_name": "AuthenticationCode2"
          }
        }
      }
    },
    "update_access_key": {
      "name": "UpdateAccessKey",
      "http_method": "POST",
      "http_path": "/",
      "input": {
        "type": "input",
        "members": {
          "user_name": {
            "type": "string",
            "serialized_name": "UserName"
          },
          "access_key_id": {
            "type": "string",
            "required": true,
            "serialized_name": "AccessKeyId"
          },
          "status": {
            "type": "string",
            "required": true,
            "serialized_name": "Status",
            "enum": [
              "Active",
              "Inactive"
            ]
          }
        }
      }
    },
    "update_account_password_policy": {
      "name": "UpdateAccountPasswordPolicy",
      "http_method": "POST",
      "http_path": "/",
      "input": {
        "type": "input",
        "members": {
          "minimum_password_length": {
            "type": "integer",
            "serialized_name": "MinimumPasswordLength"
          },
          "require_symbols": {
            "type": "boolean",
            "serialized_name": "RequireSymbols"
          },
          "require_numbers": {
            "type": "boolean",
            "serialized_name": "RequireNumbers"
          },
          "require_uppercase_characters": {
            "type": "boolean",
            "serialized_name": "RequireUppercaseCharacters"
          },
          "require_lowercase_characters": {
            "type": "boolean",
            "serialized_name": "RequireLowercaseCharacters"
          },
          "allow_users_to_change_password": {
            "type": "boolean",
            "serialized_name": "AllowUsersToChangePassword"
          }
        }
      }
    },
    "update_assume_role_policy": {
      "name": "UpdateAssumeRolePolicy",
      "http_method": "POST",
      "http_path": "/",
      "input": {
        "type": "input",
        "members": {
          "role_name": {
            "type": "string",
            "required": true,
            "serialized_name": "RoleName"
          },
          "policy_document": {
            "type": "string",
            "required": true,
            "serialized_name": "PolicyDocument"
          }
        }
      }
    },
    "update_group": {
      "name": "UpdateGroup",
      "http_method": "POST",
      "http_path": "/",
      "input": {
        "type": "input",
        "members": {
          "group_name": {
            "type": "string",
            "required": true,
            "serialized_name": "GroupName"
          },
          "new_path": {
            "type": "string",
            "serialized_name": "NewPath"
          },
          "new_group_name": {
            "type": "string",
            "serialized_name": "NewGroupName"
          }
        }
      }
    },
    "update_login_profile": {
      "name": "UpdateLoginProfile",
      "http_method": "POST",
      "http_path": "/",
      "input": {
        "type": "input",
        "members": {
          "user_name": {
            "type": "string",
            "required": true,
            "serialized_name": "UserName"
          },
          "password": {
            "type": "string",
            "required": true,
            "serialized_name": "Password"
          }
        }
      }
    },
    "update_server_certificate": {
      "name": "UpdateServerCertificate",
      "http_method": "POST",
      "http_path": "/",
      "input": {
        "type": "input",
        "members": {
          "server_certificate_name": {
            "type": "string",
            "required": true,
            "serialized_name": "ServerCertificateName"
          },
          "new_path": {
            "type": "string",
            "serialized_name": "NewPath"
          },
          "new_server_certificate_name": {
            "type": "string",
            "serialized_name": "NewServerCertificateName"
          }
        }
      }
    },
    "update_signing_certificate": {
      "name": "UpdateSigningCertificate",
      "http_method": "POST",
      "http_path": "/",
      "input": {
        "type": "input",
        "members": {
          "user_name": {
            "type": "string",
            "serialized_name": "UserName"
          },
          "certificate_id": {
            "type": "string",
            "required": true,
            "serialized_name": "CertificateId"
          },
          "status": {
            "type": "string",
            "required": true,
            "serialized_name": "Status",
            "enum": [
              "Active",
              "Inactive"
            ]
          }
        }
      }
    },
    "update_user": {
      "name": "UpdateUser",
      "http_method": "POST",
      "http_path": "/",
      "input": {
        "type": "input",
        "members": {
          "user_name": {
            "type": "string",
            "required": true,
            "serialized_name": "UserName"
          },
          "new_path": {
            "type": "string",
            "serialized_name": "NewPath"
          },
          "new_user_name": {
            "type": "string",
            "serialized_name": "NewUserName"
          }
        }
      }
    },
    "upload_server_certificate": {
      "name": "UploadServerCertificate",
      "http_method": "POST",
      "http_path": "/",
      "input": {
        "type": "input",
        "members": {
          "path": {
            "type": "string",
            "serialized_name": "Path"
          },
          "server_certificate_name": {
            "type": "string",
            "required": true,
            "serialized_name": "ServerCertificateName"
          },
          "certificate_body": {
            "type": "string",
            "required": true,
            "serialized_name": "CertificateBody"
          },
          "private_key": {
            "type": "string",
            "required": true,
            "serialized_name": "PrivateKey"
          },
          "certificate_chain": {
            "type": "string",
            "serialized_name": "CertificateChain"
          }
        }
      },
      "output": {
        "type": "output",
        "metadata": {
          "wrapper": "UploadServerCertificateResult"
        },
        "members": {
          "server_certificate_metadata": {
            "type": "structure",
            "serialized_name": "ServerCertificateMetadata",
            "members": {
              "path": {
                "type": "string",
                "serialized_name": "Path"
              },
              "server_certificate_name": {
                "type": "string",
                "serialized_name": "ServerCertificateName"
              },
              "server_certificate_id": {
                "type": "string",
                "serialized_name": "ServerCertificateId"
              },
              "arn": {
                "type": "string",
                "serialized_name": "Arn"
              },
              "upload_date": {
                "type": "iso8601_timestamp",
                "serialized_name": "UploadDate"
              }
            }
          }
        }
      }
    },
    "upload_signing_certificate": {
      "name": "UploadSigningCertificate",
      "http_method": "POST",
      "http_path": "/",
      "input": {
        "type": "input",
        "members": {
          "user_name": {
            "type": "string",
            "serialized_name": "UserName"
          },
          "certificate_body": {
            "type": "string",
            "required": true,
            "serialized_name": "CertificateBody"
          }
        }
      },
      "output": {
        "type": "output",
        "metadata": {
          "wrapper": "UploadSigningCertificateResult"
        },
        "members": {
          "certificate": {
            "type": "structure",
            "serialized_name": "Certificate",
            "members": {
              "user_name": {
                "type": "string",
                "serialized_name": "UserName"
              },
              "certificate_id": {
                "type": "string",
                "serialized_name": "CertificateId"
              },
              "certificate_body": {
                "type": "string",
                "serialized_name": "CertificateBody"
              },
              "status": {
                "type": "string",
                "serialized_name": "Status",
                "enum": [
                  "Active",
                  "Inactive"
                ]
              },
              "upload_date": {
                "type": "iso8601_timestamp",
                "serialized_name": "UploadDate"
              }
            }
          }
        }
      }
    }
  }
}